src/__init__.py
src/client.py
hubgridcloud-0.2.1.dist-info/LICENSE
hubgridcloud-0.2.1.dist-info/METADATA
hubgridcloud-0.2.1.dist-info/WHEEL
hubgridcloud-0.2.1.dist-info/top_level.txt
hubgridcloud-0.2.1.dist-info/RECORD
