Metadata-Version: 2.1
Name: hubgridcloud
Version: 0.2.1
Summary: The SimplyStack API allows you to manage Stacklets and resources within the SimplyStack cloud in a simple, programmatic way using conventional HTTP requests.
Home-page: https://github.com/null-none/python-hubgridcloud
Author: Kalinin Dmitry <kalinin.mitko@gmail.com>
License: MIT
Keywords: python,cloud,hubgridcloud,server
Classifier: Programming Language :: Python
Classifier: Programming Language :: Python :: 2.7
Classifier: Programming Language :: Python :: 3.4
Classifier: Programming Language :: Python :: 3.5
Classifier: Programming Language :: Python :: 3.6
License-File: LICENSE
Requires-Dist: requests (==2.27.1)
Requires-Dist: schema (==0.7.5)
